LICENSE
MANIFEST.in
README.md
pyproject.toml
setup.py
orthogonalstreamlines/__init__.py
orthogonalstreamlines/cablemesh.py
orthogonalstreamlines.egg-info/PKG-INFO
orthogonalstreamlines.egg-info/SOURCES.txt
orthogonalstreamlines.egg-info/dependency_links.txt
orthogonalstreamlines.egg-info/not-zip-safe
orthogonalstreamlines.egg-info/requires.txt
orthogonalstreamlines.egg-info/top_level.txt
orthogonalstreamlines/common/algebra.cpp
orthogonalstreamlines/common/algebra.h
orthogonalstreamlines/intersection/__init__.py
orthogonalstreamlines/intersection/cablenetwork.cpp
orthogonalstreamlines/intersection/cablenetwork.h
orthogonalstreamlines/intersection/fixedsizedict.cpp
orthogonalstreamlines/intersection/fixedsizedict.h
orthogonalstreamlines/intersection/intersection.cpp
orthogonalstreamlines/intersection/intersection.h
orthogonalstreamlines/intersection/runengine.pyx
orthogonalstreamlines/intersection/streamlinecollection.cpp
orthogonalstreamlines/intersection/streamlinecollection.h
orthogonalstreamlines/intersection/unionfind.cpp
orthogonalstreamlines/intersection/unionfind.h
orthogonalstreamlines/intersection/vertices.cpp
orthogonalstreamlines/intersection/vertices.h
orthogonalstreamlines/intersection/wrapper.py
orthogonalstreamlines/tessellation/__init__.py
orthogonalstreamlines/tessellation/tessellation.pyx
orthogonalstreamlines/triangulation/__init__.py
orthogonalstreamlines/triangulation/earcut.cpp
orthogonalstreamlines/triangulation/from_sage.py
orthogonalstreamlines/triangulation/lookup_tables.h
orthogonalstreamlines/triangulation/polypartition.cpp
orthogonalstreamlines/triangulation/polypartition.h
orthogonalstreamlines/triangulation/to_sage.py
orthogonalstreamlines/triangulation/triangulatefacets.cpp
orthogonalstreamlines/triangulation/triangulatefacets.h
orthogonalstreamlines/triangulation/triangulation.pyx