Metadata-Version: 2.1
Name: orthogonalstreamlines
Version: 0.1.2
Summary: Create an interconnected cable mesh from an orientation field on a triangulated 3D surface
Home-page: http://github.com/jacquemv/orthogonalstreamlines
Author: Vincent Jacquemet
Author-email: vincent.jacquemet@umontreal.ca
License: MIT
Keywords: mesh,cables,surface,streamlines
License-File: LICENSE
Requires-Dist: numpy
Requires-Dist: cython
Requires-Dist: surfacetopology
Requires-Dist: evenlyspacedstreamlines
